tinyalchemize/__init__.py
tinyalchemize/records.py
tinyalchemize/sqltable.py
tinyalchemize/table.py
tinyalchemize-0.0.3.dist-info/LICENSE
tinyalchemize-0.0.3.dist-info/METADATA
tinyalchemize-0.0.3.dist-info/WHEEL
tinyalchemize-0.0.3.dist-info/top_level.txt
tinyalchemize-0.0.3.dist-info/RECORD
